{
	"users":[
	{
		"id":"krishna",
		"password":"nemani",
		"type":"driver"
	},
	{
		"id":"sandhya",
		"password":"hrithik",
		"type":"passenger"
	},
	{
		"id":"rajini",
		"password":"rajini",
		"type":"passenger"
	},
	{
		"id":"karthik"
		"password":"karthik",
		"type":"passenger"
	},
	{
		"id":"driver1",
		"password":"driver1",
		"type":"driver"
	},
	{
		"id":"driver2",
		"password":"driver2",
		"type":"driver"
	},
	{
		"id":"driver3",
		"password":"driver3",
		"type":"driver"
	},
	{
		"id":"driver4",
		"password":"driver4",
		"type":"driver"
	},
	{
		"id":"ps1"
		"password":"ps1",
		"type":"passenger"
	},
	{
		"id":"ps2"
		"password":"ps2",
		"type":"passenger"
	},
	{
		"id":"ps3"
		"password":"ps3",
		"type":"passenger"
	}
	]
}