{"route": {"evening": [{"stop": "Other Sessions [View Morning Session]", "time": "$NA#"}, {"stop": "Saidapet Bus Stand", "time": "$NA#"}, {"stop": "T Nagar N.Usman Road - Opp To Viveks", "time": "$NA#"}, {"stop": "Nungambakkam - Choolaimedu & Railway Station", "time": "$NA#"}, {"stop": "Nelson Manikkam Road - Opp To Food World", "time": "$NA#"}, {"stop": "Anna Nagar Arch - After Signal", "time": "$NA#"}, {"stop": "Anna Nagar - Ayappa Temple", "time": "$NA#"}], "morning": [{"stop": "Morning Session [View Other Sessions]", "time": "$NA#"}, {"stop": "Anna Nagar - Ayappa Temple", "time": "7.20AM"}, {"stop": "Anna Nagar Arch - After Signal", "time": "7.25AM"}, {"stop": "Nelson Manikkam Road - Opp To Food World", "time": "7.30AM"}, {"stop": "Nungambakkam - Choolaimedu & Railway Station", "time": "7.34AM"}, {"stop": "T Nagar N.Usman Road - Opp To Viveks", "time": "7.40AM"}, {"stop": "Siruseri-Sez", "time": "9.00AM"}], "title": "Route Map for SS-05 Anna Nagar West Depot"}}